nexio_behave/__init__.py
nexio_behave/behave.ini
nexio_behave/cli_nexio_behave/__init__.py
nexio_behave/cli_nexio_behave/cli.py
nexio_behave/cli_nexio_behave/config.py
nexio_behave/cli_nexio_behave/constants.py
nexio_behave/cli_nexio_behave/runner.py
nexio_behave/default_templates/__init__.py
nexio_behave/default_templates/behave.ini
nexio_behave/default_templates/default_feature.feature
nexio_behave/default_templates/environment.py
nexio_behave/default_templates/import_steps.py
nexio_behave/environment.py
nexio_behave/models/__init__.py
nexio_behave/steps/__init__.py
nexio_behave/steps/assert_header_steps.py
nexio_behave/steps/assert_json_steps.py
nexio_behave/steps/assert_response_steps.py
nexio_behave/steps/context_steps.py
nexio_behave/steps/debug_steps.py
nexio_behave/steps/generic_request_steps.py
nexio_behave/steps/header_steps.py
nexio_behave/steps/json_steps.py
nexio_behave/steps/poc_test_steps.py
nexio_behave/test_utils/__init__.py
nexio_behave/test_utils/assertions.py
nexio_behave/test_utils/common_behave_functions.py
nexio_behave/test_utils/default_env_decorators.py
nexio_behave/test_utils/environment_functions.py
nexio_behave/test_utils/generic_requests.py
nexio_behave-0.41.0.dist-info/entry_points.txt
nexio_behave-0.41.0.dist-info/LICENSE.md
nexio_behave-0.41.0.dist-info/WHEEL
nexio_behave-0.41.0.dist-info/METADATA
nexio_behave-0.41.0.dist-info/RECORD
